{"otherData": {},"traceEvents":[{},{"cat":"function","dur":0,"name":"void SandBox2D::OnDetach(void)","ph":"X","pid":0,"tid":25964,"ts":348750774554.500},{"cat":"function","dur":1010,"name":"void Hazel::ImGuiLayer::OnDetach(void)","ph":"X","pid":0,"tid":25964,"ts":348750774602.900},{"cat":"function","dur":14823,"name":"void Hazel::WindowsWindow::Shutdown(void)","ph":"X","pid":0,"tid":25964,"ts":348750775674.400},{"cat":"function","dur":15017,"name":"Hazel::WindowsWindow::~WindowsWindow(void)","ph":"X","pid":0,"tid":25964,"ts":348750775674.300}]}